{
  "question_type": "fill_in_blanks",
  "questions": [
    {
      "id": 1,
      "question": "A list is defined using ________ brackets.",
      "answer": "square"
    },
    {
      "id": 2,
      "question": "List items are separated using ________ (comma).",
      "answer": ","
    },
    {
      "id": 3,
      "question": "The ________ function is used to find the number of items in a list.",
      "answer": "len()"
    },
    {
      "id": 4,
      "question": "The first item on a list has a positive index of ________.",
      "answer": "0"
    },
    {
      "id": 5,
      "question": "The last item on a list has a negative index of ________.",
      "answer": "-1"
    },
    {
      "id": 6,
      "question": "Negative index allows us to access the list from the ________.",
      "answer": "last"
    },
    {
      "id": 7,
      "question": "A condition in Python always returns a ________ result.",
      "answer": "Boolean"
    },
    {
      "id": 8,
      "question": "The two Boolean values in Python are ________ and ________.",
      "answer": "True and False"
    },
    {
      "id": 9,
      "question": "The relational operator > means ________.",
      "answer": "greater than"
    },
    {
      "id": 10,
      "question": "The relational operator >= means ________.",
      "answer": "greater than or equal to"
    },
    {
      "id": 11,
      "question": "The relational operator < means ________.",
      "answer": "lesser than"
    },
    {
      "id": 12,
      "question": "The relational operator <= means ________.",
      "answer": "lesser than or equal to"
    },
    {
      "id": 13,
      "question": "The relational operator == means ________.",
      "answer": "equal to"
    },
    {
      "id": 14,
      "question": "The relational operator != means ________.",
      "answer": "not equal to"
    },
    {
      "id": 15,
      "question": "In Python, ________ is used to define blocks of code.",
      "answer": "indentation"
    },
    {
      "id": 16,
      "question": "To indent code, we insert a ________ or tab key at the beginning of each line.",
      "answer": "whitespace"
    },
    {
      "id": 17,
      "question": "Conditional statements are used to make ________ in Python.",
      "answer": "decisions"
    },
    {
      "id": 18,
      "question": "The for loop can be used to ________ through sequences.",
      "answer": "iterate"
    },
    {
      "id": 19,
      "question": "Iterate means to go through ________ by element.",
      "answer": "element"
    },
    {
      "id": 20,
      "question": "The range function has three parameters: ________, stop and step.",
      "answer": "start"
    },
    {
      "id": 21,
      "question": "In range function, the start value is ________ (included).",
      "answer": "inclusive"
    },
    {
      "id": 22,
      "question": "In range function, the stop value is ________ (not included).",
      "answer": "exclusive"
    },
    {
      "id": 23,
      "question": "If range has only one argument, it represents the ________ value.",
      "answer": "stop"
    },
    {
      "id": 24,
      "question": "If range has only one argument, the start value is by default ________.",
      "answer": "0"
    },
    {
      "id": 25,
      "question": "To count backwards, we use a ________ step value.",
      "answer": "negative"
    },
    {
      "id": 26,
      "question": "The time.sleep(1) function adds a delay of ________ second.",
      "answer": "1"
    },
    {
      "id": 27,
      "question": "To use time.sleep(), we must first ________ the time module.",
      "answer": "import"
    },
    {
      "id": 28,
      "question": "The % operator in Python gives the ________ of division.",
      "answer": "remainder"
    },
    {
      "id": 29,
      "question": "If n % 2 == 0, then n is an ________ number.",
      "answer": "even"
    },
    {
      "id": 30,
      "question": "If n % 2 != 0, then n is an ________ number.",
      "answer": "odd"
    },
    {
      "id": 31,
      "question": "To print the range (10, 0, -1): for x in range(10, ________, -1)",
      "answer": "0"
    },
    {
      "id": 32,
      "question": "To print 3 6 9...30: for x in range(3, ________, 3)",
      "answer": "31"
    },
    {
      "id": 33,
      "question": "To print 5 10 15...100: for x in range(5, ________, 5)",
      "answer": "101"
    },
    {
      "id": 34,
      "question": "To print 2 4 6 8 10: for x in range(2, ________, 2)",
      "answer": "11"
    },
    {
      "id": 35,
      "question": "To print 10 8 6 4 2 0: for x in range(10, ________, -2)",
      "answer": "-1"
    },
    {
      "id": 36,
      "question": "In list subjects = [\"English\", \"Tamil\", \"Maths\"], the item at index 0 is ________.",
      "answer": "English"
    },
    {
      "id": 37,
      "question": "In list fruits[len(fruits)-1], this expression gives the ________ element.",
      "answer": "last"
    },
    {
      "id": 38,
      "question": "A list can be ordered, unordered, changeable and allows ________ members.",
      "answer": "duplicate"
    },
    {
      "id": 39,
      "question": "The minimum age to vote in India is ________ years.",
      "answer": "18"
    },
    {
      "id": 40,
      "question": "A person aged ________ or above is considered a senior citizen.",
      "answer": "60"
    },
    {
      "id": 41,
      "question": "The index of the second element in a list is ________.",
      "answer": "1"
    },
    {
      "id": 42,
      "question": "The index of the third element in a list is ________.",
      "answer": "2"
    },
    {
      "id": 43,
      "question": "The negative index of the second last element is ________.",
      "answer": "-2"
    },
    {
      "id": 44,
      "question": "The negative index of the third last element is ________.",
      "answer": "-3"
    },
    {
      "id": 45,
      "question": "In for loop, the variable takes each ________ one by one.",
      "answer": "element"
    },
    {
      "id": 46,
      "question": "range(10) produces numbers from 0 to ________.",
      "answer": "9"
    },
    {
      "id": 47,
      "question": "range(1, 20) produces numbers from 1 to ________.",
      "answer": "19"
    },
    {
      "id": 48,
      "question": "range(5, 15, 2) produces ________, 7, 9, 11, 13.",
      "answer": "5"
    },
    {
      "id": 49,
      "question": "To print multiples of 5 from 5 to 50: range(5, ________, 5).",
      "answer": "51"
    },
    {
      "id": 50,
      "question": "To print multiples of 10 from 10 to 100: range(10, ________, 10).",
      "answer": "101"
    },
    {
      "id": 51,
      "question": "The ________ statement is used to exit a loop early.",
      "answer": "break"
    },
    {
      "id": 52,
      "question": "The ________ statement is used to skip the current iteration.",
      "answer": "continue"
    },
    {
      "id": 53,
      "question": "If 10 % 3 = 1, then 10 divided by 3 has a remainder of ________.",
      "answer": "1"
    },
    {
      "id": 54,
      "question": "If n % 5 == 0, then n is ________ by 5.",
      "answer": "divisible"
    },
    {
      "id": 55,
      "question": "The ________ function converts a string to an integer.",
      "answer": "int()"
    },
    {
      "id": 56,
      "question": "The ________ function converts a number to a string.",
      "answer": "str()"
    },
    {
      "id": 57,
      "question": "In list = [10, 20, 30], list[0] returns ________.",
      "answer": "10"
    },
    {
      "id": 58,
      "question": "In list = [10, 20, 30], list[-1] returns ________.",
      "answer": "30"
    },
    {
      "id": 59,
      "question": "In list = [10, 20, 30], list[1] returns ________.",
      "answer": "20"
    },
    {
      "id": 60,
      "question": "The ________ operator performs floor division in Python.",
      "answer": "//"
    },
    {
      "id": 61,
      "question": "15 // 4 gives ________ as the result.",
      "answer": "3"
    },
    {
      "id": 62,
      "question": "17 % 5 gives ________ as the result.",
      "answer": "2"
    },
    {
      "id": 63,
      "question": "20 % 4 gives ________ as the result.",
      "answer": "0"
    },
    {
      "id": 64,
      "question": "If age = 25, then age >= 18 is ________.",
      "answer": "True"
    },
    {
      "id": 65,
      "question": "If age = 15, then age >= 18 is ________.",
      "answer": "False"
    },
    {
      "id": 66,
      "question": "In 'for x in \"HELLO\":', x takes each ________ of the string.",
      "answer": "character"
    },
    {
      "id": 67,
      "question": "len(\"Python\") returns ________.",
      "answer": "6"
    },
    {
      "id": 68,
      "question": "len([]) returns ________ for an empty list.",
      "answer": "0"
    },
    {
      "id": 69,
      "question": "To print numbers 100, 90, 80, 70... 10: range(100, ________, -10).",
      "answer": "0"
    },
    {
      "id": 70,
      "question": "A list can contain data of ________ types.",
      "answer": "different"
    },
    {
      "id": 71,
      "question": "The input() function always returns data as a ________.",
      "answer": "string"
    },
    {
      "id": 72,
      "question": "To use time.sleep(), we write ________ time at the top.",
      "answer": "import"
    },
    {
      "id": 73,
      "question": "time.sleep(2) pauses the program for ________ seconds.",
      "answer": "2"
    },
    {
      "id": 74,
      "question": "range(0, 10, 2) produces ________ even numbers.",
      "answer": "5"
    },
    {
      "id": 75,
      "question": "range(1, 10, 2) produces ________ odd numbers.",
      "answer": "5"
    },
    {
      "id": 76,
      "question": "The statement inside if block executes when condition is ________.",
      "answer": "True"
    },
    {
      "id": 77,
      "question": "The statement inside else block executes when condition is ________.",
      "answer": "False"
    },
    {
      "id": 78,
      "question": "In list = [\"a\", \"b\", \"c\", \"d\", \"e\"], the middle element is ________.",
      "answer": "c"
    },
    {
      "id": 79,
      "question": "In list = [\"a\", \"b\", \"c\", \"d\", \"e\"], the middle index is ________.",
      "answer": "2"
    },
    {
      "id": 80,
      "question": "range(5, 5) produces ________ elements.",
      "answer": "0"
    }
  ]
}
