{
  "question_type": "true_false",
  "questions": [
    {"id": "tf001", "statement": "Length is a fundamental quantity.", "answer": true, "explanation": "Length is one of the seven fundamental quantities in the SI system.", "source_section": "Fundamental Quantities"},
    {"id": "tf002", "statement": "The SI unit of mass is gram.", "answer": false, "explanation": "The SI unit of mass is kilogram (kg), not gram.", "source_section": "SI Units"},
    {"id": "tf003", "statement": "Vernier callipers can measure internal as well as external dimensions.", "answer": true, "explanation": "Vernier callipers have both external jaws and internal jaws for these measurements.", "source_section": "Vernier Callipers"},
    {"id": "tf004", "statement": "Velocity is a scalar quantity.", "answer": false, "explanation": "Velocity is a vector quantity as it has both magnitude and direction.", "source_section": "Scalar and Vector"},
    {"id": "tf005", "statement": "The least count of a screw gauge is smaller than that of vernier callipers.", "answer": true, "explanation": "Screw gauge least count is 0.01 mm, while vernier callipers is 0.1 mm.", "source_section": "Measuring Instruments"},
    {"id": "tf006", "statement": "1 light year is a unit of time.", "answer": false, "explanation": "Light year is a unit of distance, equal to the distance traveled by light in one year.", "source_section": "Large Units"},
    {"id": "tf007", "statement": "Force is a derived quantity.", "answer": true, "explanation": "Force = mass × acceleration, derived from fundamental quantities mass, length, and time.", "source_section": "Derived Quantities"},
    {"id": "tf008", "statement": "The pitch of a screw gauge is 0.01 mm.", "answer": false, "explanation": "The pitch of a standard screw gauge is 1 mm. The least count is 0.01 mm.", "source_section": "Screw Gauge"},
    {"id": "tf009", "statement": "Angle is a dimensionless quantity.", "answer": true, "explanation": "Angle = arc/radius = length/length, making it dimensionless.", "source_section": "Dimensions"},
    {"id": "tf010", "statement": "The prefix 'kilo' represents 10^6.", "answer": false, "explanation": "Kilo represents 10^3 (thousand). Mega represents 10^6.", "source_section": "Prefixes"},
    {"id": "tf011", "statement": "There are 10 divisions on the vernier scale of a standard vernier callipers.", "answer": true, "explanation": "A standard vernier callipers has 10 divisions on the vernier scale.", "source_section": "Vernier Callipers"},
    {"id": "tf012", "statement": "Newton is a fundamental unit.", "answer": false, "explanation": "Newton is a derived unit of force (kg·m/s²).", "source_section": "SI Units"},
    {"id": "tf013", "statement": "Dimensional analysis can determine the numerical constants in equations.", "answer": false, "explanation": "Dimensional analysis cannot determine dimensionless numerical constants.", "source_section": "Dimensional Analysis"},
    {"id": "tf014", "statement": "1 angstrom is larger than 1 nanometre.", "answer": false, "explanation": "1 Å = 10^-10 m, while 1 nm = 10^-9 m. So nanometre is larger.", "source_section": "Small Units"},
    {"id": "tf015", "statement": "The ratchet in a screw gauge helps in applying uniform pressure.", "answer": true, "explanation": "The ratchet ensures consistent pressure is applied during measurement.", "source_section": "Screw Gauge"},
    {"id": "tf016", "statement": "Work and torque have different dimensions.", "answer": false, "explanation": "Both have the same dimensions [M L^2 T^-2], though they represent different concepts.", "source_section": "Dimensions"},
    {"id": "tf017", "statement": "Zero error always gives a reading less than the true value.", "answer": false, "explanation": "Positive zero error gives higher readings; negative gives lower readings.", "source_section": "Errors"},
    {"id": "tf018", "statement": "Kelvin is the SI unit of temperature.", "answer": true, "explanation": "Kelvin (K) is the SI fundamental unit of thermodynamic temperature.", "source_section": "SI Units"},
    {"id": "tf019", "statement": "A physical quantity can be completely described by its magnitude alone if it is a vector.", "answer": false, "explanation": "Vectors need both magnitude and direction; scalars need only magnitude.", "source_section": "Scalar and Vector"},
    {"id": "tf020", "statement": "The vernier scale slides along the main scale.", "answer": true, "explanation": "The vernier scale (with movable jaw) slides along the fixed main scale.", "source_section": "Vernier Callipers"},
    {"id": "tf021", "statement": "1 fermi is equal to 10^-15 metres.", "answer": true, "explanation": "1 fermi (femtometre) = 10^-15 m, used for nuclear dimensions.", "source_section": "Small Units"},
    {"id": "tf022", "statement": "Speed and velocity have the same dimensions.", "answer": true, "explanation": "Both have dimensions [L T^-1], though velocity is a vector.", "source_section": "Dimensions"},
    {"id": "tf023", "statement": "The CGS unit of force is Newton.", "answer": false, "explanation": "The CGS unit of force is dyne. Newton is the SI unit.", "source_section": "CGS System"},
    {"id": "tf024", "statement": "Precision and accuracy mean the same thing in measurement.", "answer": false, "explanation": "Accuracy is closeness to true value; precision is consistency of readings.", "source_section": "Errors"},
    {"id": "tf025", "statement": "Electric current is a fundamental quantity in SI system.", "answer": true, "explanation": "Electric current (ampere) is one of the seven SI fundamental quantities.", "source_section": "Fundamental Quantities"},
    {"id": "tf026", "statement": "The circular scale of a screw gauge usually has 50 divisions.", "answer": false, "explanation": "A standard screw gauge has 100 divisions on its circular scale.", "source_section": "Screw Gauge"},
    {"id": "tf027", "statement": "Joule and Newton-metre have the same dimensions.", "answer": true, "explanation": "Both are units of energy/work with dimensions [M L^2 T^-2].", "source_section": "Units"},
    {"id": "tf028", "statement": "A metre scale can measure lengths up to 0.1 mm accurately.", "answer": false, "explanation": "A metre scale typically has least count of 1 mm, not 0.1 mm.", "source_section": "Measuring Instruments"},
    {"id": "tf029", "statement": "The dimension formula [M L^2 T^-3] represents power.", "answer": true, "explanation": "Power = Work/Time = [M L^2 T^-2]/[T] = [M L^2 T^-3].", "source_section": "Dimensions"},
    {"id": "tf030", "statement": "Specific gravity has a unit.", "answer": false, "explanation": "Specific gravity is the ratio of densities, so it is unitless and dimensionless.", "source_section": "Derived Quantities"}
  ],
  "total_count": 30,
  "generated_at": "2026-01-16T12:00:00",
  "subject": "Physics",
  "chapter": "Physical Quantities"
}
